erptools/__init__.py
erptools/context.py
erptools/creator.py
erptools/email.py
erptools/erpmodel.py
erptools/erpviews.py
erptools/exception_handler.py
erptools/microservices.py
erptools/pagination.py
erptools/pdf2.py
erptools/serializers.py
erptools/signals.py
erptools/sqs.py
erptools/storage.py
erptools/utility.py
erptools/erp_tests/__init__.py
erptools/erp_tests/accounts_tests.py
erptools/erp_tests/base_test.py
erptools/erp_tests/generate_account_objects.py
erp_utils-0.1.137.dist-info/METADATA
erp_utils-0.1.137.dist-info/WHEEL
erp_utils-0.1.137.dist-info/top_level.txt
erp_utils-0.1.137.dist-info/RECORD
